shapedtw/__init__.py
shapedtw/dtwPlot.py
shapedtw/exceptions.py
shapedtw/preprocessing.py
shapedtw/shapeDescriptors.py
shapedtw/shapedtw.py
shapedtw/utils.py
shapedtw-1.0.3.dist-info/LICENSE
shapedtw-1.0.3.dist-info/METADATA
shapedtw-1.0.3.dist-info/WHEEL
shapedtw-1.0.3.dist-info/top_level.txt
shapedtw-1.0.3.dist-info/RECORD
