Metadata-Version: 2.1
Name: shapedtw
Version: 1.0.3
Summary: An extension to the dtw-python package, implementing a variant of the dtw algorithm called 'shape dtw'.
Home-page: https://mikolajszafraniecupds.github.io/shapedtw-python/
Author: Mikołaj Szafraniec
Author-email: mikolaj.szafraniec.upds@gmail.com
License: GNU General Public License v3
Keywords: dtw,shapedtw,timeseries
Classifier: Development Status :: 3 - Alpha
Classifier: Intended Audience :: Science/Research
Classifier: Intended Audience :: Financial and Insurance Industry
Classifier: Topic :: Scientific/Engineering
Classifier: License :: OSI Approved :: GNU General Public License v2 or later (GPLv2+)
Classifier: Natural Language :: English
Classifier: Programming Language :: Python :: 3.9
Classifier: Programming Language :: Python :: 3.10
Classifier: Programming Language :: Python :: 3.11
Classifier: Programming Language :: Python :: 3.12
Requires-Python: >=3.9
License-File: LICENSE
Requires-Dist: numpy (>=1.22)
Requires-Dist: scipy (>=1.8)
Requires-Dist: dtw-python (>=1.3)
Requires-Dist: PyWavelets (>=1.3)
Requires-Dist: pandas (>=1.5)
Requires-Dist: matplotlib (>=3.5)
